openmind_datasets/__init__.py
openmind_datasets/conf.py
openmind_datasets/datasets_adaptor.py
openmind_datasets/ms_adaptor.py
openmind_datasets/ms/__init__.py
openmind_datasets/ms/ms_ds_convertor.py
openmind_datasets/ms/ms_formatter.py
openmind_datasets/patches/__init__.py
openmind_datasets/patches/info.py
openmind_datasets/patches/streaming_download_manager.py
openmind_datasets/utils/__init__.py
openmind_datasets/utils/logging.py
openmind_datasets/utils/warning.py
openmind_datasets-0.7.1.dist-info/METADATA
openmind_datasets-0.7.1.dist-info/WHEEL
openmind_datasets-0.7.1.dist-info/licenses/LICENSE
openmind_datasets-0.7.1.dist-info/RECORD
