Metadata-Version: 2.4
Name: openmind_datasets
Version: 0.7.1
Summary: The openmind-datasets is a product which allows you to use datasets in modelers community.
Project-URL: Homepage, https://gitee.com/foundation-models/openmind-datasets
Project-URL: Repository, https://gitee.com/foundation-models/openmind-datasets
Author-email: The openmind-datasets Team <contact@openmind.cn>
License:                                  Apache License
License-File: LICENSE
Classifier: Development Status :: 1 - Planning
Classifier: Intended Audience :: Developers
Classifier: Intended Audience :: Education
Classifier: Intended Audience :: Science/Research
Classifier: License :: OSI Approved :: Apache Software License
Classifier: Operating System :: OS Independent
Classifier: Programming Language :: Python :: 3
Classifier: Programming Language :: Python :: 3.8
Classifier: Programming Language :: Python :: 3.9
Classifier: Programming Language :: Python :: 3.10
Classifier: Topic :: Scientific/Engineering :: Artificial Intelligence
Requires-Python: >=3.8
Requires-Dist: datasets==2.18.0
Requires-Dist: huggingface-hub
Requires-Dist: openmind-hub
Requires-Dist: setuptools
Provides-Extra: lint
Requires-Dist: black; extra == 'lint'
Requires-Dist: ruff; extra == 'lint'
Provides-Extra: test
Requires-Dist: pytest; extra == 'test'
Requires-Dist: pytest-cov; extra == 'test'
